crowley_frame/__init__.py
crowley_frame/_crowley.cp310-win_amd64.pyd
crowley_frame/api.py
crowley_frame/col.py
crowley_frame/pipe.py
crowleyframe-0.2.0.dist-info/METADATA
crowleyframe-0.2.0.dist-info/WHEEL
crowleyframe-0.2.0.dist-info/RECORD
