Metadata-Version: 2.4
Name: crowleyframe
Version: 0.2.0
Classifier: Development Status :: 3 - Alpha
Classifier: Intended Audience :: Science/Research
Classifier: Intended Audience :: Developers
Classifier: License :: OSI Approved :: MIT License
Classifier: Programming Language :: Python
Classifier: Programming Language :: Python :: 3
Classifier: Programming Language :: Python :: 3 :: Only
Classifier: Programming Language :: Rust
Classifier: Topic :: Scientific/Engineering :: Information Analysis
Classifier: Topic :: Software Development :: Libraries
Requires-Dist: pandas>=1.5
Requires-Dist: numpy>=1.23
Summary: A Rust-powered, tidyverse-inspired DataFrame manipulation library for Python.
Keywords: dataframe,data-analysis,tidyverse,dplyr,tidyr,rust,pyo3
Author-email: Adam Ezzat <adamezzat24@gmail.com>
License: MIT
Requires-Python: >=3.8
Project-URL: Homepage, https://github.com/AdamEzzat1/crowley-frame
Project-URL: Repository, https://github.com/AdamEzzat1/crowley-frame
Project-URL: Issues, https://github.com/AdamEzzat1/crowley-frame
